MultiSpecX/__init__.py
MultiSpecX-0.1.0.dist-info/LICENSE
MultiSpecX-0.1.0.dist-info/METADATA
MultiSpecX-0.1.0.dist-info/WHEEL
MultiSpecX-0.1.0.dist-info/top_level.txt
MultiSpecX-0.1.0.dist-info/RECORD
